simplepbr/__init__.py
simplepbr/_ibl_funcs_cpu.py
simplepbr/_shaderutils.py
simplepbr/envmap.py
simplepbr/envpool.py
simplepbr/hdr2env.py
simplepbr/logging.py
simplepbr/py.typed
simplepbr/shaders.py
simplepbr/textures.py
simplepbr/utils.py
simplepbr/version.py
panda3d_simplepbr-0.12.0.dist-info/LICENSE.txt
panda3d_simplepbr-0.12.0.dist-info/METADATA
panda3d_simplepbr-0.12.0.dist-info/WHEEL
panda3d_simplepbr-0.12.0.dist-info/entry_points.txt
panda3d_simplepbr-0.12.0.dist-info/top_level.txt
panda3d_simplepbr-0.12.0.dist-info/RECORD
