Metadata-Version: 2.1
Name: panda3d-simplepbr
Version: 0.12.0
Summary: A straight-forward, easy-to-use, drop-in, PBR replacement for Panda3D's builtin auto shader
Author: Mitchell Stokes
License: BSD-3-Clause
Project-URL: homepage, https://github.com/Moguri/panda3d-simplepbr
Keywords: panda3d,gamedev,pbr
Classifier: Development Status :: 4 - Beta
Classifier: License :: OSI Approved :: BSD License
Classifier: Programming Language :: Python :: 3
Requires-Python: >=3.8
License-File: LICENSE.txt
Requires-Dist: panda3d>=1.10.8
Requires-Dist: typing_extensions~=4.7
Provides-Extra: test
Requires-Dist: pytest; extra == "test"
Requires-Dist: pylint~=3.0.0; extra == "test"
Requires-Dist: pytest-pylint; extra == "test"
